query_limiter/__init__.py
query_limiter/exceptions.py
query_limiter/formatting.py
query_limiter/limiter.py
query_limiter/query.py
django_query_limiter-0.2.0.dist-info/LICENSE
django_query_limiter-0.2.0.dist-info/METADATA
django_query_limiter-0.2.0.dist-info/WHEEL
django_query_limiter-0.2.0.dist-info/top_level.txt
django_query_limiter-0.2.0.dist-info/RECORD
