Metadata-Version: 2.1
Name: django-query-limiter
Version: 0.2.0
Summary: Limit django query amounts in a certain scope
Author: Raven De Vooght
License: BSD 3-Clause License
Project-URL: Homepage, https://github.com/TWRaven/django-query-limiter
Keywords: django,query,limit,performance
Classifier: Programming Language :: Python
Classifier: Programming Language :: Python :: 3
License-File: LICENSE
Requires-Dist: django
Provides-Extra: formatting
Requires-Dist: sqlparse ; extra == 'formatting'
Requires-Dist: humanize ; extra == 'formatting'
